Workbook
Name Slicer_Product_type: #N/A
Name Slicer_Product_type1: #N/A
Name Slicer_Supplier_name: #N/A
Name Slicer_Supplier_name1: #N/A
Name Slicer_Transportation_modes: #N/A
Name Slicer_Transportation_modes1: #N/A

Sheet SupplyData
A1: Product type | B1: SKU | C1: Price | D1: Availability | E1: Number of products sold | F1: Revenue generated | G1: Customer demographics | H1: Stock levels | I1: Lead times | J1: Order quantities | K1: Shipping times | L1: Shipping carriers | M1: Shipping costs | N1: Supplier name | O1: Location | P1: Lead time | Q1: Production volumes | R1: Manufacturing lead time | S1: Manufacturing costs | T1: Inspection results | U1: Defect rates | V1: Transportation modes | W1: Routes | X1: Costs | Z1: Revenue per Unit Sold | AA1: cost per unit | AB1: shipping cost % | AC1: inventory risk | AD1: profit margin | AE1: profit margin %
A2: haircare | B2: SKU0 | C2: 69.808006 | D2: 55 | E2: 802 | F2: 8661.9968 | G2: Female | H2: 58 | I2: 7 | J2: 96 | K2: 4 | L2: Carrier B | M2: 2.9565721 | N2: Supplier 3 | O2: Mumbai | P2: 29 | Q2: 215 | R2: 29 | S2: 46.279879 | T2: Pending | U2: 0.22641036 | V2: Road | W2: Route B | X2: 187.75208 | Z2: =SupplyData[[#This Row],[Revenue generated]]/SupplyData[[#This Row],[Number of products sold]] -> 10.800495 | AA2: =SupplyData[[#This Row],[Manufacturing costs]]/SupplyData[[#This Row],[Production volumes]] -> 0.21525525 | AB2: =SupplyData[[#This Row],[Costs]]/SupplyData[[#This Row],[Revenue generated]] -> 0.02167538 | AC2: =IF(AND(H2<30,I2>15),"High",IF(H2<60,"Medium","Low")) -> Medium | AD2: =F2-S2-X2 -> 8427.9648 | AE2: =AD2/F2 -> 0.97298175
A3: skincare | B3: SKU1 | C3: 14.843523 | D3: 95 | E3: 736 | F3: 7460.9001 | G3: Female | H3: 53 | I3: 30 | J3: 37 | K3: 2 | L3: Carrier A | M3: 9.7165748 | N3: Supplier 3 | O3: Mumbai | P3: 23 | Q3: 517 | R3: 30 | S3: 33.616769 | T3: Pending | U3: 4.854068 | V3: Road | W3: Route B | X3: 503.06558 | Z3: =SupplyData[[#This Row],[Revenue generated]]/SupplyData[[#This Row],[Number of products sold]] -> 10.137092 | AA3: =SupplyData[[#This Row],[Manufacturing costs]]/SupplyData[[#This Row],[Production volumes]] -> 0.065022764 | AB3: =SupplyData[[#This Row],[Costs]]/SupplyData[[#This Row],[Revenue generated]] -> 0.067426929 | AC3: =IF(AND(H3<30,I3>15),"High",IF(H3<60,"Medium","Low")) -> Medium | AD3: =F3-S3-X3 -> 6924.2177 | AE3: =AD3/F3 -> 0.92806735
A4: haircare | B4: SKU2 | C4: 11.319683 | D4: 34 | E4: 8 | F4: 9577.7496 | G4: Unknown | H4: 1 | I4: 10 | J4: 88 | K4: 2 | L4: Carrier B | M4: 8.0544793 | N4: Supplier 1 | O4: Mumbai | P4: 12 | Q4: 971 | R4: 27 | S4: 30.688019 | T4: Pending | U4: 4.5805926 | V4: Air | W4: Route C | X4: 141.92028 | Z4: =SupplyData[[#This Row],[Revenue generated]]/SupplyData[[#This Row],[Number of products sold]] -> 1197.2187 | AA4: =SupplyData[[#This Row],[Manufacturing costs]]/SupplyData[[#This Row],[Production volumes]] -> 0.031604551 | AB4: =SupplyData[[#This Row],[Costs]]/SupplyData[[#This Row],[Revenue generated]] -> 0.014817706 | AC4: =IF(AND(H4<30,I4>15),"High",IF(H4<60,"Medium","Low")) -> Medium | AD4: =F4-S4-X4 -> 9405.1413 | AE4: =AD4/F4 -> 0.9819782
A5: skincare | B5: SKU3 | C5: 61.163343 | D5: 68 | E5: 83 | F5: 7766.8364 | G5: Female | H5: 23 | I5: 13 | J5: 59 | K5: 6 | L5: Carrier C | M5: 1.7295686 | N5: Supplier 5 | O5: Kolkata | P5: 24 | Q5: 937 | R5: 18 | S5: 35.624741 | T5: Fail | U5: 4.7466486 | V5: Rail | W5: Route A | X5: 254.77616 | Z5: =SupplyData[[#This Row],[Revenue generated]]/SupplyData[[#This Row],[Number of products sold]] -> 93.576342 | AA5: =SupplyData[[#This Row],[Manufacturing costs]]/SupplyData[[#This Row],[Production volumes]] -> 0.038020001 | AB5: =SupplyData[[#This Row],[Costs]]/SupplyData[[#This Row],[Revenue generated]] -> 0.03280308 | AC5: =IF(AND(H5<30,I5>15),"High",IF(H5<60,"Medium","Low")) -> Medium | AD5: =F5-S5-X5 -> 7476.4355 | AE5: =AD5/F5 -> 0.96261014
A6: skincare | B6: SKU4 | C6: 4.805496 | D6: 26 | E6: 871 | F6: 2686.5052 | G6: Male | H6: 5 | I6: 3 | J6: 56 | K6: 8 | L6: Carrier A | M6: 3.8905479 | N6: Supplier 1 | O6: Delhi | P6: 5 | Q6: 414 | R6: 3 | S6: 92.065161 | T6: Fail | U6: 3.1455795 | V6: Air | W6: Route A | X6: 923.44063 | Z6: =SupplyData[[#This Row],[Revenue generated]]/SupplyData[[#This Row],[Number of products sold]] -> 3.0843917 | AA6: =SupplyData[[#This Row],[Manufacturing costs]]/SupplyData[[#This Row],[Production volumes]] -> 0.22237961 | AB6: =SupplyData[[#This Row],[Costs]]/SupplyData[[#This Row],[Revenue generated]] -> 0.34373306 | AC6: =IF(AND(H6<30,I6>15),"High",IF(H6<60,"Medium","Low")) -> Medium | AD6: =F6-S6-X6 -> 1670.9994 | AE6: =AD6/F6 -> 0.62199745
A7: haircare | B7: SKU5 | C7: 1.699976 | D7: 87 | E7: 147 | F7: 2828.3487 | G7: Female | H7: 90 | I7: 27 | J7: 66 | K7: 3 | L7: Carrier B | M7: 4.4440989 | N7: Supplier 4 | O7: Bangalore | P7: 10 | Q7: 104 | R7: 17 | S7: 56.766476 | T7: Fail | U7: 2.7791935 | V7: Road | W7: Route A | X7: 235.46124 | Z7: =SupplyData[[#This Row],[Revenue generated]]/SupplyData[[#This Row],[Number of products sold]] -> 19.240468 | AA7: =SupplyData[[#This Row],[Manufacturing costs]]/SupplyData[[#This Row],[Production volumes]] -> 0.5458315 | AB7: =SupplyData[[#This Row],[Costs]]/SupplyData[[#This Row],[Revenue generated]] -> 0.083250426 | AC7: =IF(AND(H7<30,I7>15),"High",IF(H7<60,"Medium","Low")) -> Low | AD7: =F7-S7-X7 -> 2536.121 | AE7: =AD7/F7 -> 0.89667904
A8: skincare | B8: SKU6 | C8: 4.0783329 | D8: 48 | E8: 65 | F8: 7823.4766 | G8: Male | H8: 11 | I8: 15 | J8: 58 | K8: 8 | L8: Carrier C | M8: 3.8807633 | N8: Supplier 3 | O8: Kolkata | P8: 14 | Q8: 314 | R8: 24 | S8: 1.0850686 | T8: Pending | U8: 1.0009106 | V8: Sea | W8: Route A | X8: 134.3691 | Z8: =SupplyData[[#This Row],[Revenue generated]]/SupplyData[[#This Row],[Number of products sold]] -> 120.36118 | AA8: =SupplyData[[#This Row],[Manufacturing costs]]/SupplyData[[#This Row],[Production volumes]] -> 0.0034556324 | AB8: =SupplyData[[#This Row],[Costs]]/SupplyData[[#This Row],[Revenue generated]] -> 0.017175113 | AC8: =IF(AND(H8<30,I8>15),"High",IF(H8<60,"Medium","Low")) -> Medium | AD8: =F8-S8-X8 -> 7688.0224 | AE8: =AD8/F8 -> 0.98268619
A9: cosmetics | B9: SKU7 | C9: 42.958384 | D9: 59 | E9: 426 | F9: 8496.1038 | G9: Female | H9: 93 | I9: 17 | J9: 11 | K9: 1 | L9: Carrier B | M9: 2.3483388 | N9: Supplier 4 | O9: Bangalore | P9: 22 | Q9: 564 | R9: 1 | S9: 99.466109 | T9: Fail | U9: 0.39817719 | V9: Road | W9: Route C | X9: 802.05631 | Z9: =SupplyData[[#This Row],[Revenue generated]]/SupplyData[[#This Row],[Number of products sold]] -> 19.943906 | AA9: =SupplyData[[#This Row],[Manufacturing costs]]/SupplyData[[#This Row],[Production volumes]] -> 0.17635835 | AB9: =SupplyData[[#This Row],[Costs]]/SupplyData[[#This Row],[Revenue generated]] -> 0.094402838 | AC9: =IF(AND(H9<30,I9>15),"High",IF(H9<60,"Medium","Low")) -> Low | AD9: =F9-S9-X9 -> 7594.5814 | AE9: =AD9/F9 -> 0.8938899
A10: cosmetics | B10: SKU8 | C10: 68.717597 | D10: 78 | E10: 150 | F10: 7517.3632 | G10: Female | H10: 5 | I10: 10 | J10: 15 | K10: 7 | L10: Carrier C | M10: 3.4047339 | N10: Supplier 4 | O10: Mumbai | P10: 13 | Q10: 769 | R10: 8 | S10: 11.423027 | T10: Pending | U10: 2.7098627 | V10: Sea | W10: Route B | X10: 505.55713 | Z10: =SupplyData[[#This Row],[Revenue generated]]/SupplyData[[#This Row],[Number of products sold]] -> 50.115755 | AA10: =SupplyData[[#This Row],[Manufacturing costs]]/SupplyData[[#This Row],[Production volumes]] -> 0.014854392 | AB10: =SupplyData[[#This Row],[Costs]]/SupplyData[[#This Row],[Revenue generated]] -> 0.067251923 | AC10: =IF(AND(H10<30,I10>15),"High",IF(H10<60,"Medium","Low")) -> Medium | AD10: =F10-S10-X10 -> 7000.383 | AE10: =AD10/F10 -> 0.93122852
A11: skincare | B11: SKU9 | C11: 64.015733 | D11: 35 | E11: 980 | F11: 4971.146 | G11: Unknown | H11: 14 | I11: 27 | J11: 83 | K11: 1 | L11: Carrier A | M11: 7.1666453 | N11: Supplier 2 | O11: Chennai | P11: 29 | Q11: 963 | R11: 23 | S11: 47.957602 | T11: Pending | U11: 3.8446145 | V11: Rail | W11: Route B | X11: 995.92946 | Z11: =SupplyData[[#This Row],[Revenue generated]]/SupplyData[[#This Row],[Number of products sold]] -> 5.0725979 | AA11: =SupplyData[[#This Row],[Manufacturing costs]]/SupplyData[[#This Row],[Production volumes]] -> 0.049800209 | AB11: =SupplyData[[#This Row],[Costs]]/SupplyData[[#This Row],[Revenue generated]] -> 0.20034203 | AC11: =IF(AND(H11<30,I11>15),"High",IF(H11<60,"Medium","Low")) -> High | AD11: =F11-S11-X11 -> 3927.2589 | AE11: =AD11/F11 -> 0.79001078
A12: skincare | B12: SKU10 | C12: 15.707796 | D12: 11 | E12: 996 | F12: 2330.9658 | G12: Male | H12: 51 | I12: 13 | J12: 80 | K12: 2 | L12: Carrier C | M12: 8.6732112 | N12: Supplier 5 | O12: Kolkata | P12: 18 | Q12: 830 | R12: 5 | S12: 96.527353 | T12: Pass | U12: 1.7273139 | V12: Road | W12: Route B | X12: 806.10318 | Z12: =SupplyData[[#This Row],[Revenue generated]]/SupplyData[[#This Row],[Number of products sold]] -> 2.3403271 | AA12: =SupplyData[[#This Row],[Manufacturing costs]]/SupplyData[[#This Row],[Production volumes]] -> 0.11629802 | AB12: =SupplyData[[#This Row],[Costs]]/SupplyData[[#This Row],[Revenue generated]] -> 0.34582368 | AC12: =IF(AND(H12<30,I12>15),"High",IF(H12<60,"Medium","Low")) -> Medium | AD12: =F12-S12-X12 -> 1428.3353 | AE12: =AD12/F12 -> 0.61276543
A13: skincare | B13: SKU11 | C13: 90.63546 | D13: 95 | E13: 960 | F13: 6099.9441 | G13: Female | H13: 46 | I13: 23 | J13: 60 | K13: 1 | L13: Carrier A | M13: 4.5239431 | N13: Supplier 2 | O13: Kolkata | P13: 28 | Q13: 362 | R13: 11 | S13: 27.592363 | T13: Pending | U13: 0.021169821 | V13: Air | W13: Route A | X13: 126.72303 | Z13: =SupplyData[[#This Row],[Revenue generated]]/SupplyData[[#This Row],[Number of products sold]] -> 6.3541085 | AA13: =SupplyData[[#This Row],[Manufacturing costs]]/SupplyData[[#This Row],[Production volumes]] -> 0.076221997 | AB13: =SupplyData[[#This Row],[Costs]]/SupplyData[[#This Row],[Revenue generated]] -> 0.020774458 | AC13: =IF(AND(H13<30,I13>15),"High",IF(H13<60,"Medium","Low")) -> Medium | AD13: =F13-S13-X13 -> 5945.6287 | AE13: =AD13/F13 -> 0.97470216
... A101: haircare | B101: SKU99 | C101: 68.517833 | D101: 17 | E101: 627 | F101: 9185.1858 | G101: Unknown | H101: 55 | I101: 8 | J101: 59 | K101: 6 | L101: Carrier B | M101: 1.3110238 | N101: Supplier 2 | O101: Chennai | P101: 29 | Q101: 921 | R101: 2 | S101: 38.072899 | T101: Fail | U101: 0.34602729 | V101: Rail | W101: Route B | X101: 210.74301 | Z101: =SupplyData[[#This Row],[Revenue generated]]/SupplyData[[#This Row],[Number of products sold]] -> 14.649419 | AA101: =SupplyData[[#This Row],[Manufacturing costs]]/SupplyData[[#This Row],[Production volumes]] -> 0.041338652 | AB101: =SupplyData[[#This Row],[Costs]]/SupplyData[[#This Row],[Revenue generated]] -> 0.022943794 | AC101: =IF(AND(H101<30,I101>15),"High",IF(H101<60,"Medium","Low")) -> Medium | AD101: =F101-S101-X101 -> 8936.3699 | AE101: =AD101/F101 -> 0.97291117

Sheet PivotTables
A1: Pivot Tables
A3: Row Labels | B3: Sum of Revenue generated | C3: Sum of Number of products sold
A4: skincare | B4: 241628.16 | C4: 20731
A5: haircare | B5: 174455.39 | C5: 13611
A6: cosmetics | B6: 161521.27 | C6: 11757
A7: Grand Total | B7: 577604.82 | C7: 46099
F25: Row Labels | G25: Average of Lead times | L25: Row Labels | M25: Sum of Revenue generated
A26: Row Labels | B26: Average of Defect rates | F26: Supplier 4 | G26: 17 | L26: Supplier 1 | M26: 157529
A27: Supplier 5 | B27: 2.6654083 | F27: Supplier 1 | G27: 16.777778 | L27: Supplier 2 | M27: 125467.42
A28: Supplier 3 | B28: 2.465786 | F28: Supplier 2 | G28: 16.227273 | L28: Supplier 5 | M28: 110343.46
A29: Supplier 2 | B29: 2.3627501 | F29: Supplier 5 | G29: 14.722222 | L29: Supplier 3 | M29: 97795.98
A30: Supplier 4 | B30: 2.3373974 | F30: Supplier 3 | G30: 14.333333 | L30: Supplier 4 | M30: 86468.962
A31: Supplier 1 | B31: 1.8036297 | F31: Grand Total | G31: 15.96 | L31: Grand Total | M31: 577604.82
A32: Grand Total | B32: 2.277158
A50: Row Labels | B50: Average of Shipping costs | C50: Average of Lead time | E50: Row Labels | F50: Sum of Revenue generated
A51: Road | B51: 5.5421154 | C51: 18.034483 | E51: Rail | F51: 164990.42
A52: Rail | B52: 5.4690979 | C52: 17.535714 | E52: Road | F52: 159315.23
A53: Sea | B53: 4.9702938 | C53: 16.411765 | E53: Air | F53: 155735.35
A54: Air | B54: 6.0178394 | C54: 15.961538 | E54: Sea | F54: 97563.819
A55: Grand Total | B55: 5.5481491 | C55: 17.08 | E55: Grand Total | F55: 577604.82
A75: Row Labels | B75: Count of SKU | E75: Row Labels | F75: Average of Revenue generated
A76: Medium | B76: 49 | E76: High | F76: 6262.682
A77: Low | B77: 37 | E77: Medium | F77: 5924.0351
A78: High | B78: 14 | E78: Low | F78: 5395.9338
A79: Grand Total | B79: 100 | E79: Grand Total | F79: 5776.0482
A100: Row Labels | B100: Average of Revenue generated | C100: Sum of Number of products sold
A101: Female | B101: 6019.7896 | C101: 18571
A102: Male | B102: 5680.7021 | C102: 12317
A103: Unknown | B103: 5583.5527 | C103: 15211
A104: Grand Total | B104: 5776.0482 | C104: 46099

Sheet Dashboard
A1: Supply Chain Performance Dashboard
A3: Total Revenue | B3: Products Sold | C3: Average Lead Time | D3: Average Shipping Cost | E3: Average Defect Rate | F3: Average Profit Margin
A4: =SUM(SupplyData!F:F) -> 577604.82 | B4: =SUM(SupplyData!E:E) -> 46099 | C4: =AVERAGE(SupplyData!I:I) -> 15.96 | D4: =AVERAGE(SupplyData!K:K) -> 5.75 | E4: =AVERAGE(SupplyData!U:U) -> 2.277158 | F4: =AVERAGE(SupplyData!AE:AE) -> 0.86206079
A48: Recommendations
A50: Products with low stock levels and long lead times were identified as the highest inventory risk. Long lead times should be a priority to decrease.
A52: Supplier performance varied significantly, with some suppliers showing higher defect rates than others.
A54: Transportation mode affected shipping costs and delivery times. Sea may be very underutilized depending on the source and destination.
A56: Higher-margin products may be good candidates for additional inventory investment.
A58: Road transportation offers the lowest average shipping cost, while Air provides the shortest lead time. Road transportation should remain to be prioritized other than scenarios where air is the only possible option.
A60: High-risk SKUs should be prioritized for replenishment due to low stock levels and longer lead times.
A62: Supplier 3 has the second highest average defect rate and should be reviewed for quality improvements, despite them having the lowest lead time.
